[
    {
        "id": "1",
        "content": "Follow the footsteps into the water.",
        "story_id": "1"
    },
    {
        "id": "2",
        "content": "Your curiosity steers you toward the falls.",
        "story_id": "1"
    },
    {
        "id": "3",
        "content": "Choice for second story page",
        "story_id": "2"
    },
    {
        "id": "4",
        "content": "Second choice for second story page",
        "story_id": "2"
    },
    {
        "id": "5",
        "content": "Choice for third story page",
        "story_id": "3"
    },
    {
        "id": "6",
        "content": "Second choice for third story page",
        "story_id": "3"
    }
]